src/__init__.py
src/cli/__init__.py
src/cli/main.py
src/whisper/__init__.py
src/whisper/subtitles.py
src/whisper/transcribe.py
src/youtube/__init__.py
src/youtube/download.py
ytws-0.4.3.dist-info/licenses/LICENSE
ytws-0.4.3.dist-info/METADATA
ytws-0.4.3.dist-info/WHEEL
ytws-0.4.3.dist-info/entry_points.txt
ytws-0.4.3.dist-info/top_level.txt
ytws-0.4.3.dist-info/RECORD
