Metadata-Version: 2.4
Name: ytws
Version: 0.4.3
Summary: YouTube Whisper - A YouTube Downloader with Transcription
Home-page: https://github.com/faker2048/youtube-whisper
Author: faker2048
Author-email: nspyia2002@gmail.com
Classifier: Development Status :: 3 - Alpha
Classifier: Intended Audience :: Developers
Classifier: License :: OSI Approved :: MIT License
Classifier: Programming Language :: Python :: 3
Classifier: Programming Language :: Python :: 3.8
Classifier: Programming Language :: Python :: 3.9
Classifier: Programming Language :: Python :: 3.10
Classifier: Programming Language :: Python :: 3.11
Classifier: Programming Language :: Python :: 3.12
License-File: LICENSE
Requires-Dist: click>=8.1.6
Requires-Dist: faster_whisper>=0.10.0
Requires-Dist: loguru>=0.7.0
Requires-Dist: yt_dlp>=2024.4.9
Dynamic: author
Dynamic: author-email
Dynamic: classifier
Dynamic: description
Dynamic: description-content-type
Dynamic: home-page
Dynamic: license-file
Dynamic: requires-dist
Dynamic: summary
